cdk_comprehend_s3olap/__init__.py
cdk_comprehend_s3olap/py.typed
cdk_comprehend_s3olap/_jsii/__init__.py
cdk_comprehend_s3olap/_jsii/cdk-comprehend-s3olap@2.0.527.jsii.tgz
cdk_comprehend_s3olap-2.0.527.dist-info/LICENSE
cdk_comprehend_s3olap-2.0.527.dist-info/METADATA
cdk_comprehend_s3olap-2.0.527.dist-info/WHEEL
cdk_comprehend_s3olap-2.0.527.dist-info/top_level.txt
cdk_comprehend_s3olap-2.0.527.dist-info/RECORD
